stakeshare/__init__.py
stakeshare/client.py
stakeshare/errors.py
stakeshare/utils.py
stakeshare_client-0.1b3.dist-info/METADATA
stakeshare_client-0.1b3.dist-info/WHEEL
stakeshare_client-0.1b3.dist-info/top_level.txt
stakeshare_client-0.1b3.dist-info/RECORD
