Metadata-Version: 2.1
Name: stakeshare-client
Version: 0.1b3
Summary: StakeShare RPC client
Home-page: https://github.com/mrmm/stakeshare-python
Author: Ronittos
Author-email: ronittos.dorittoss@gmail.com
License: Apache 2.0
Platform: UNKNOWN
Requires-Dist: requests (>=2.21.0)
